[
  {
    "title": "Xtreme Gym",
    "cid": "5195851610684797513",
    "stars": 4.8,
    "reviews": 4859,
    "category": "Gym",
    "address": "Old No 3, New No 5, 2nd Floor, Xtreme Gym, Rama, 2nd Street, Vandavasi, Tamil Nadu 604408",
    "completePhoneNumber": "093844 60454",
    "url": ""
  },
  {
    "title": "TIGER FITNESS STUDIO",
    "cid": "16355493679029294763",
    "stars": 4.6,
    "reviews": 4638,
    "category": "Gym",
    "address": "Vandavasi, Tamil Nadu 604408",
    "completePhoneNumber": "097874 96199",
    "url": ""
  },
  {
    "title": "Park and gym free 24 hours",
    "cid": "2934481125556481863",
    "stars": 3.8,
    "reviews": 386,
    "category": "Park",
    "address": "GJ38 G4G Park and gym free 24 hours, Vandavasi, Tamil Nadu 604408",
    "completePhoneNumber": "",
    "url": ""
  }
]